bicm/__init__.py
bicm/graph_classes.py
bicm/models_functions.py
bicm/network_functions.py
bicm/poibin.py
bicm/solver_functions.py
tests/BiCM_test.py
tests/__init__.py
bicm-3.4.0.dist-info/LICENSE.txt
bicm-3.4.0.dist-info/METADATA
bicm-3.4.0.dist-info/WHEEL
bicm-3.4.0.dist-info/top_level.txt
bicm-3.4.0.dist-info/RECORD
