Metadata-Version: 2.1
Name: bicm
Version: 3.4.0
Summary: Package for bipartite configuration model
Home-page: https://github.com/mat701/BiCM
Author: Matteo Bruno
Author-email: matteobruno180@gmail.com
Classifier: Programming Language :: Python :: 3
Classifier: Programming Language :: Python :: 3.5
Classifier: Programming Language :: Python :: 3.6
Classifier: Programming Language :: Python :: 3.7
Classifier: Programming Language :: Python :: 3.8
Classifier: License :: OSI Approved :: MIT License
Classifier: Operating System :: OS Independent
Requires-Python: >=3.5
License-File: LICENSE.txt
Requires-Dist: numpy (>=1.14)
Requires-Dist: scipy (>=1.4)
Requires-Dist: tqdm (>=4.52.0)
Requires-Dist: numba (>=0.52.0)
